vemmio_client/__init__.py
vemmio_client/accelerometer.proto
vemmio_client/accelerometer_pb2.py
vemmio_client/accelerometer_pb2.pyi
vemmio_client/addon.proto
vemmio_client/addon_pb2.py
vemmio_client/addon_pb2.pyi
vemmio_client/admin.proto
vemmio_client/admin_pb2.py
vemmio_client/admin_pb2.pyi
vemmio_client/battery.proto
vemmio_client/battery_pb2.py
vemmio_client/battery_pb2.pyi
vemmio_client/ble.proto
vemmio_client/ble_pb2.py
vemmio_client/ble_pb2.pyi
vemmio_client/bsensor.proto
vemmio_client/bsensor_pb2.py
vemmio_client/bsensor_pb2.pyi
vemmio_client/carbon_dioxide.proto
vemmio_client/carbon_dioxide_pb2.py
vemmio_client/carbon_dioxide_pb2.pyi
vemmio_client/carbon_monoxide.proto
vemmio_client/carbon_monoxide_pb2.py
vemmio_client/carbon_monoxide_pb2.pyi
vemmio_client/color.proto
vemmio_client/color_pb2.py
vemmio_client/color_pb2.pyi
vemmio_client/configuration.proto
vemmio_client/configuration_pb2.py
vemmio_client/configuration_pb2.pyi
vemmio_client/const.py
vemmio_client/devices.proto
vemmio_client/devices_pb2.py
vemmio_client/devices_pb2.pyi
vemmio_client/door.proto
vemmio_client/door_pb2.py
vemmio_client/door_pb2.pyi
vemmio_client/doorbell.proto
vemmio_client/doorbell_pb2.py
vemmio_client/doorbell_pb2.pyi
vemmio_client/emergency.proto
vemmio_client/emergency_pb2.py
vemmio_client/emergency_pb2.pyi
vemmio_client/firmware.proto
vemmio_client/firmware_pb2.py
vemmio_client/firmware_pb2.pyi
vemmio_client/flood.proto
vemmio_client/flood_pb2.py
vemmio_client/flood_pb2.pyi
vemmio_client/gate.proto
vemmio_client/gate_pb2.py
vemmio_client/gate_pb2.pyi
vemmio_client/gateway.proto
vemmio_client/gateway_pb2.py
vemmio_client/gateway_pb2.pyi
vemmio_client/heartbeat.proto
vemmio_client/heartbeat_pb2.py
vemmio_client/heartbeat_pb2.pyi
vemmio_client/info.proto
vemmio_client/info_pb2.py
vemmio_client/info_pb2.pyi
vemmio_client/level.proto
vemmio_client/level_pb2.py
vemmio_client/level_pb2.pyi
vemmio_client/lock.proto
vemmio_client/lock_pb2.py
vemmio_client/lock_pb2.pyi
vemmio_client-0.2.1.dist-info/LICENSE
vemmio_client-0.2.1.dist-info/METADATA
vemmio_client-0.2.1.dist-info/WHEEL
vemmio_client-0.2.1.dist-info/RECORD
